wosfile/__init__.py
wosfile/read.py
wosfile/record.py
wosfile/tags.py
wosfile-0.6.dist-info/LICENSE
wosfile-0.6.dist-info/METADATA
wosfile-0.6.dist-info/WHEEL
wosfile-0.6.dist-info/top_level.txt
wosfile-0.6.dist-info/RECORD
