Metadata-Version: 2.1
Name: wosfile
Version: 0.6
Summary: Handle Web of Science export files
Home-page: http://github.com/rafguns/wosfile
Author: Raf Guns
Author-email: raf.guns@uantwerpen.be
License: New BSD License
Platform: any
Classifier: Intended Audience :: Science/Research
Classifier: Intended Audience :: Developers
Classifier: License :: OSI Approved
Classifier: Programming Language :: Python :: 3.6
Classifier: Programming Language :: Python :: 3.7
Classifier: Programming Language :: Python :: 3.8
Classifier: Programming Language :: Python :: 3.9
Classifier: Programming Language :: Python :: 3.10
Classifier: Topic :: Software Development
Classifier: Topic :: Scientific/Engineering
Classifier: Development Status :: 3 - Alpha
Classifier: Natural Language :: English
Classifier: Operating System :: OS Independent
License-File: LICENSE
